cocotb_amba-0.1.2.dist-info/METADATA
cocotb_amba-0.1.2.dist-info/WHEEL
cocotb_amba-0.1.2.dist-info/entry_points.txt
cocotb_amba-0.1.2.dist-info/licenses/LICENSE
cocotb_amba/__init__.py
cocotb_amba/ahb_driver.py
cocotb_amba/apb_driver.py
cocotb_amba-0.1.2.dist-info/RECORD
