Metadata-Version: 2.1
Name: cocotb-amba
Version: 0.1.2
Summary: Collection of AMBA Masters and Slaves for cocotb
Classifier: Programming Language :: Python :: 3
Classifier: Operating System :: OS Independent
Project-URL: Homepage, https://github.com/nbiotcloud/cocotb-amba
Project-URL: Documentation, https://cocotb-amba.readthedocs.io/en/stable/
Project-URL: Bug Tracker, https://github.com/nbiotcloud/cocotb-amba/issues
Requires-Python: <4.0,>=3.10.0
Requires-Dist: cocotb>=1.9.2
Requires-Dist: humannum>=1.1.1
